aiogram_dialog_extras/__init__.py
aiogram_dialog_extras/exceptions.py
aiogram_dialog_extras/types.py
aiogram_dialog_extras/handlers/__init__.py
aiogram_dialog_extras/handlers/context.py
aiogram_dialog_extras/manager/__init__.py
aiogram_dialog_extras/manager/dialog.py
aiogram_dialog_extras/middlewares/__init__.py
aiogram_dialog_extras/middlewares/environment.py
aiogram_dialog_extras/middlewares/i18n.py
aiogram_dialog_extras/middlewares/throttling.py
aiogram_dialog_extras/models/__init__.py
aiogram_dialog_extras/models/text.py
aiogram_dialog_extras/utils/__init__.py
aiogram_dialog_extras/utils/context.py
aiogram_dialog_extras/utils/throttling.py
aiogram_dialog_extras/widgets/__init__.py
aiogram_dialog_extras/widgets/kbd/__init__.py
aiogram_dialog_extras/widgets/kbd/select.py
aiogram_dialog_extras/widgets/kbd/state.py
aiogram_dialog_extras/widgets/media/__init__.py
aiogram_dialog_extras/widgets/media/dynamic.py
aiogram_dialog_extras/widgets/text/__init__.py
aiogram_dialog_extras/widgets/text/breakline.py
aiogram_dialog_extras/widgets/text/format.py
aiogram_dialog_extras/widgets/text/lang.py
aiogram_dialog_extras-0.1.2.dist-info/LICENSE
aiogram_dialog_extras-0.1.2.dist-info/METADATA
aiogram_dialog_extras-0.1.2.dist-info/WHEEL
aiogram_dialog_extras-0.1.2.dist-info/top_level.txt
aiogram_dialog_extras-0.1.2.dist-info/RECORD
